{
  "page": 5,
  "productsCount": 16,
  "scrapedAt": "2025-02-08T12:13:56.273Z",
  "products": [
    {
      "title": "FMP13x1",
      "price": "From GH₵380.00",
      "image": "//prettyhairstores.com/cdn/shop/files/45A446DA-190C-48E5-B2CC-A2056177683E.jpg?v=1737979496&width=165",
      "url": "https://prettyhairstores.com/products/fmp13x1"
    },
    {
      "title": "Frgstw #",
      "price": "From GH₵280.00",
      "image": "//prettyhairstores.com/cdn/shop/files/62142EAA-148F-4D99-B9EC-CFA5B4BBE101.jpg?v=1738268166&width=165",
      "url": "https://prettyhairstores.com/products/frgstw"
    },
    {
      "title": "Frontal lace blade",
      "price": "GH₵10.00",
      "image": "//prettyhairstores.com/cdn/shop/files/413481C4-F42A-494C-A329-6C16208FFCE8.jpg?v=1737998757&width=165",
      "url": "https://prettyhairstores.com/products/frontal-lace-blade"
    },
    {
      "title": "Frontal ponytail",
      "price": "From GH₵320.00",
      "image": "//prettyhairstores.com/cdn/shop/files/FEB44A3F-AD35-4ADF-AB19-D6649CF3A17A.jpg?v=1733341142&width=165",
      "url": "https://prettyhairstores.com/products/frontal-ponytail"
    },
    {
      "title": "FRSTW",
      "price": "From GH₵790.00",
      "image": "//prettyhairstores.com/cdn/shop/files/C3855FF6-EE47-41F4-837A-3848ADCD6013.jpg?v=1738150275&width=165",
      "url": "https://prettyhairstores.com/products/frstw"
    },
    {
      "title": "FYCAR#1",
      "price": "From GH₵750.00",
      "image": "//prettyhairstores.com/cdn/shop/files/1E8B9233-9BDF-4F9D-B518-E7C3DF16429E.jpg?v=1738018132&width=165",
      "url": "https://prettyhairstores.com/products/fycar-1"
    },
    {
      "title": "FYCAR4x4",
      "price": "GH₵450.00",
      "image": "//prettyhairstores.com/cdn/shop/files/1E8B9233-9BDF-4F9D-B518-E7C3DF16429E.jpg?v=1738018132&width=165",
      "url": "https://prettyhairstores.com/products/fycar4x4"
    },
    {
      "title": "FYNSTW/1",
      "price": "From GH₵1,000.00",
      "image": "//prettyhairstores.com/cdn/shop/files/AFC8FCF1-79A3-4C45-B3E4-1A91B879107A.jpg?v=1737840364&width=165",
      "url": "https://prettyhairstores.com/products/fynstw-1"
    },
    {
      "title": "Gele frontal",
      "price": "From GH₵300.00",
      "image": "//prettyhairstores.com/cdn/shop/files/6A85CD8E-779F-4509-AFBC-2B1E5298653D.jpg?v=1738867188&width=165",
      "url": "https://prettyhairstores.com/products/gele-frontal"
    },
    {
      "title": "Ghost bond",
      "price": "GH₵20.00",
      "image": "//prettyhairstores.com/cdn/shop/files/B21F88BF-F1A6-4154-A275-B27E428D54FE.jpg?v=1732039380&width=165",
      "url": "https://prettyhairstores.com/products/ghost-bond"
    },
    {
      "title": "GLG#1",
      "price": "GH₵100.00",
      "image": "//prettyhairstores.com/cdn/shop/files/E99B904C-52EF-477F-8F6E-C2A615336A76.jpg?v=1737825565&width=165",
      "url": "https://prettyhairstores.com/products/glg-1"
    },
    {
      "title": "Glgjc",
      "price": "GH₵230.00",
      "image": "//prettyhairstores.com/cdn/shop/files/3CDAEF15-8CDE-4330-9DBC-ECAF2D501281.jpg?v=1738022092&width=165",
      "url": "https://prettyhairstores.com/products/glgjc"
    },
    {
      "title": "Glgjc",
      "price": "GH₵130.00",
      "image": "//prettyhairstores.com/cdn/shop/files/3CDAEF15-8CDE-4330-9DBC-ECAF2D501281.jpg?v=1738022092&width=165",
      "url": "https://prettyhairstores.com/products/glgjc-1"
    },
    {
      "title": "GLGN1",
      "price": "GH₵100.00",
      "image": "//prettyhairstores.com/cdn/shop/files/9FAF5D5B-391B-4DC4-AF16-7B329DF7F827.jpg?v=1737751305&width=165",
      "url": "https://prettyhairstores.com/products/glgn1"
    },
    {
      "title": "GLGN1",
      "price": "GH₵235.00",
      "image": "//prettyhairstores.com/cdn/shop/files/93D6BE65-40CA-4FBF-AA43-023242791865.jpg?v=1737751608&width=165",
      "url": "https://prettyhairstores.com/products/glgn1-1"
    },
    {
      "title": "Glowy deep wave + closure",
      "price": "From GH₵770.00",
      "image": "//prettyhairstores.com/cdn/shop/files/1849D921-B544-4277-A465-171C13F8CD3B.jpg?v=1737987716&width=165",
      "url": "https://prettyhairstores.com/products/glowy-deep-wave-closure"
    }
  ]
}