{
  "page": 3,
  "productsCount": 16,
  "scrapedAt": "2025-02-08T12:13:47.903Z",
  "products": [
    {
      "title": "BBR#1",
      "price": "From GH₵260.00",
      "image": "//prettyhairstores.com/cdn/shop/files/1E0501FC-A2D7-434B-BFA5-6E22D885B407.jpg?v=1737924840&width=165",
      "url": "https://prettyhairstores.com/products/bbr-1"
    },
    {
      "title": "Bellestar curl detangling spray",
      "price": "GH₵35.00",
      "image": "//prettyhairstores.com/cdn/shop/files/1F07A064-3765-4EF2-A324-B5D2DE8B4F68.jpg?v=1732384663&width=165",
      "url": "https://prettyhairstores.com/products/bellestar-curl-detangling-spray"
    },
    {
      "title": "Big Afro hair",
      "price": "GH₵650.00",
      "image": "//prettyhairstores.com/cdn/shop/files/5474A4B6-95E9-48D9-98C3-F2BA114F5B0B.jpg?v=1733597614&width=165",
      "url": "https://prettyhairstores.com/products/big-afro-hair"
    },
    {
      "title": "BLBS",
      "price": "GH₵1,200.00",
      "image": "//prettyhairstores.com/cdn/shop/files/BD612882-5BD7-4EC1-BF10-70E2AB954EE9.jpg?v=1738952582&width=165",
      "url": "https://prettyhairstores.com/products/blbs"
    },
    {
      "title": "Bold hold rotating curler",
      "price": "GH₵370.00",
      "image": "//prettyhairstores.com/cdn/shop/files/45E2292A-9636-4B26-AD3E-206D30920740.jpg?v=1737998474&width=165",
      "url": "https://prettyhairstores.com/products/bold-hold-rotating-curler"
    },
    {
      "title": "BPXRY#1",
      "price": "GH₵330.00",
      "image": "//prettyhairstores.com/cdn/shop/files/A393A9DC-54AC-4901-B23B-9413DF13021D.jpg?v=1737978603&width=165",
      "url": "https://prettyhairstores.com/products/bpxry-1"
    },
    {
      "title": "Brand new hot comb",
      "price": "GH₵115.00",
      "image": "//prettyhairstores.com/cdn/shop/files/7FF9BDA9-5C4E-4D4B-88BE-6AE62BE638B7.jpg?v=1737747174&width=165",
      "url": "https://prettyhairstores.com/products/brand-new-hot-comb"
    },
    {
      "title": "BSQU/#4",
      "price": "From GH₵700.00",
      "image": "//prettyhairstores.com/cdn/shop/files/D5315E56-C2E8-4441-91BE-7775A97E146A.jpg?v=1737982265&width=165",
      "url": "https://prettyhairstores.com/products/bsqu-4"
    },
    {
      "title": "BWRY#22",
      "price": "From GH₵1,350.00",
      "image": "//prettyhairstores.com/cdn/shop/files/32CB493B-2227-46C1-AD6A-7C504D051DE9.jpg?v=1737921997&width=165",
      "url": "https://prettyhairstores.com/products/bwry-22"
    },
    {
      "title": "Carribean curl for real",
      "price": "From GH₵100.00",
      "image": "//prettyhairstores.com/cdn/shop/files/694D76DA-1B01-41FE-A9E1-E0514F76CEFB.jpg?v=1733052328&width=165",
      "url": "https://prettyhairstores.com/products/carribean-curl-for-real"
    },
    {
      "title": "CassDw",
      "price": "GH₵330.00",
      "image": "//prettyhairstores.com/cdn/shop/files/BE9B6810-915D-4161-B63E-2885F666A000.jpg?v=1738018404&width=165",
      "url": "https://prettyhairstores.com/products/cassdw"
    },
    {
      "title": "Coco bounce",
      "price": "GH₵430.00",
      "image": "//prettyhairstores.com/cdn/shop/files/195D35D2-CBDD-4458-9CB0-8C172A399E12.jpg?v=1739003076&width=165",
      "url": "https://prettyhairstores.com/products/coco-bounce"
    },
    {
      "title": "Code: JCRY#1",
      "price": "From GH₵900.00",
      "image": "//prettyhairstores.com/cdn/shop/files/A335EFE4-DBEC-418F-8EA6-B5F139239253.jpg?v=1738217771&width=165",
      "url": "https://prettyhairstores.com/products/code-jcry-1"
    },
    {
      "title": "Colorant hair dye",
      "price": "GH₵60.00",
      "image": "//prettyhairstores.com/cdn/shop/files/C8639C6F-F71C-4BBF-BFED-4AF258861099.jpg?v=1737989804&width=165",
      "url": "https://prettyhairstores.com/products/colorant-hair-dye"
    },
    {
      "title": "Control Clips",
      "price": "GH₵15.00",
      "image": "//prettyhairstores.com/cdn/shop/files/WhatsAppImage2024-10-19at16.23.57_63f9a6ee.jpg?v=1729795761&width=165",
      "url": "https://prettyhairstores.com/products/control-clips"
    },
    {
      "title": "Daisy fringe",
      "price": "From GH₵300.00",
      "image": "//prettyhairstores.com/cdn/shop/files/4798D99F-2F37-490E-ABD8-7B0239DE7CDC.jpg?v=1733259140&width=165",
      "url": "https://prettyhairstores.com/products/daisy-fringe"
    }
  ]
}